_rtmixer.abi3.so
rtmixer.py
rtmixer-0.1.7.dist-info/RECORD
rtmixer-0.1.7.dist-info/LICENSE
rtmixer-0.1.7.dist-info/WHEEL
rtmixer-0.1.7.dist-info/top_level.txt
rtmixer-0.1.7.dist-info/METADATA
