Metadata-Version: 2.1
Name: rtmixer
Version: 0.1.7
Summary: Reliable low-latency audio playback and recording
Home-page: https://python-rtmixer.readthedocs.io/
Author: Matthias Geier
Author-email: Matthias.Geier@gmail.com
License: MIT
Keywords: sound,audio,PortAudio,realtime,low-latency
Platform: any
Classifier: License :: OSI Approved :: MIT License
Classifier: Operating System :: OS Independent
Classifier: Programming Language :: Python
Classifier: Programming Language :: Python :: 3
Classifier: Topic :: Multimedia :: Sound/Audio
Requires-Python: >=3.6
License-File: LICENSE
Requires-Dist: CFFI >=1
Requires-Dist: pa-ringbuffer
Requires-Dist: sounddevice >0.3.9
